odoo8_addon_account_bank_statement_import_mt940_nl_rabo-8.0.1.1.1-py2.7-nspkg.pth
odoo_addons/account_bank_statement_import_mt940_nl_rabo/account_bank_statement_import.py
odoo_addons/account_bank_statement_import_mt940_nl_rabo/__openerp__.py
odoo_addons/account_bank_statement_import_mt940_nl_rabo/__init__.py
odoo_addons/account_bank_statement_import_mt940_nl_rabo/README.rst
odoo_addons/account_bank_statement_import_mt940_nl_rabo/mt940.py
odoo_addons/account_bank_statement_import_mt940_nl_rabo/i18n/es.po
odoo_addons/account_bank_statement_import_mt940_nl_rabo/i18n/lt_LT.po
odoo_addons/account_bank_statement_import_mt940_nl_rabo/i18n/sl.po
odoo_addons/account_bank_statement_import_mt940_nl_rabo/i18n/nl.po
odoo_addons/account_bank_statement_import_mt940_nl_rabo/i18n/de.po
odoo_addons/account_bank_statement_import_mt940_nl_rabo/i18n/fr.po
odoo_addons/account_bank_statement_import_mt940_nl_rabo/i18n/pt_BR.po
odoo_addons/account_bank_statement_import_mt940_nl_rabo/test_files/test-rabo.swi
odoo_addons/account_bank_statement_import_mt940_nl_rabo/tests/__init__.py
odoo_addons/account_bank_statement_import_mt940_nl_rabo/tests/test_import_bank_statement.py
odoo8_addon_account_bank_statement_import_mt940_nl_rabo-8.0.1.1.1.dist-info/top_level.txt
odoo8_addon_account_bank_statement_import_mt940_nl_rabo-8.0.1.1.1.dist-info/WHEEL
odoo8_addon_account_bank_statement_import_mt940_nl_rabo-8.0.1.1.1.dist-info/RECORD
odoo8_addon_account_bank_statement_import_mt940_nl_rabo-8.0.1.1.1.dist-info/metadata.json
odoo8_addon_account_bank_statement_import_mt940_nl_rabo-8.0.1.1.1.dist-info/DESCRIPTION.rst
odoo8_addon_account_bank_statement_import_mt940_nl_rabo-8.0.1.1.1.dist-info/METADATA
odoo8_addon_account_bank_statement_import_mt940_nl_rabo-8.0.1.1.1.dist-info/namespace_packages.txt
